[
  {
    "id": "2510360745",
    "area": "105",
    "feature": "满二",
    "title": "105平3室2厅2卫！三面朝阳，采光超好！首付3万，剩余首付分期3年",
    "xiaoqu_": "亚星江南小镇",
    "room": "3室2厅",
    "total_price": "65",
    "url": "http://m.fang.com/esf/zz/JHAGT_180406091_17143738x2510360745_165086179.html",
    "price": "6190元/㎡ ",
    "louceng": "中层/26层",
    "louxing": "板楼",
    "chaoxiang": "南北",
    "zhuangxiu": "毛坯",
    "age": "2018",
    "quyu": "上街-上街",
    "shoufu": "",
    "xiaoqu": "亚星江南小镇",
    "position": 1
  },
  {
    "id": "2510360745",
    "area": "116",
    "feature": "满五",
    "title": "亚星江南小镇3室1厅2卫",
    "xiaoqu_": "亚星江南小镇",
    "room": "3室1厅",
    "total_price": "75",
    "url": "http://m.fang.com/esf/zz/JHAGT_180787192_17581872x2510360745_166278554.html",
    "price": "6466元/㎡ ",
    "louceng": "低层/31层",
    "louxing": "板楼",
    "chaoxiang": "东北",
    "zhuangxiu": "毛坯",
    "age": "2020",
    "quyu": "上街-上街",
    "shoufu": "",
    "xiaoqu": "亚星江南小镇",
    "position": 2
  }
]