[
  {
    "id": "2510147273",
    "area": "88",
    "feature": "满五",
    "title": "南三环 特价优惠房 送精装 高品质 学府居 四面环公园",
    "xiaoqu_": "郑州绿地城",
    "room": "3室2厅",
    "total_price": "102",
    "url": "http://m.fang.com/esf/zz/JHAGT_180853694_17395205x2510147273_165305460.html",
    "price": "11591元/㎡ ",
    "louceng": "中层/32层",
    "louxing": "板楼",
    "chaoxiang": "南北",
    "zhuangxiu": "精装修",
    "age": "有",
    "quyu": "2018",
    "": "二七-万客来",
    "shoufu": "",
    "xiaoqu": "郑州绿地城",
    "position": 1
  },
  {
    "id": "2510147273",
    "area": "89.6",
    "feature": "满五",
    "title": "绿地精装三房，全明采光，中间楼层，送大阳台华侨城旁",
    "xiaoqu_": "郑州绿地城",
    "room": "3室2厅",
    "total_price": "100",
    "url": "http://m.fang.com/esf/zz/JHAGT_180850843_17501017x2510147273_166788219.html",
    "price": "11161元/㎡ ",
    "louceng": "中层/27层",
    "louxing": "板楼",
    "chaoxiang": "南",
    "zhuangxiu": "精装修",
    "age": "有",
    "quyu": "2019",
    "": "二七-万客来",
    "shoufu": "",
    "xiaoqu": "郑州绿地城",
    "position": 2
  },
  {
    "id": "2510147273",
    "area": "96",
    "feature": "满五",
    "title": "南三环千亩大盘品质开发商绿地花语城",
    "xiaoqu_": "郑州绿地城",
    "room": "3室2厅",
    "total_price": "105",
    "url": "http://m.fang.com/esf/zz/JHAGT_180800649_17606933x2510147273_166698510.html",
    "price": "10938元/㎡ ",
    "louceng": "中层/23层",
    "louxing": "板楼",
    "chaoxiang": "南",
    "zhuangxiu": "精装修",
    "age": "有",
    "quyu": "2014",
    "": "二七-万客来",
    "shoufu": "",
    "xiaoqu": "郑州绿地城",
    "position": 3
  },
  {
    "id": "2510147273",
    "area": "125",
    "feature": "",
    "title": "急售，绿地开发，精装修住宅，双气，南北通透，采光好",
    "xiaoqu_": "郑州绿地城",
    "room": "3室2厅",
    "total_price": "139",
    "url": "http://m.fang.com/esf/zz/JHAGT_180759062_17551967x2510147273_166723852.html",
    "price": "11120元/㎡ ",
    "louceng": "低层/29层",
    "louxing": "板楼",
    "chaoxiang": "南",
    "zhuangxiu": "精装修",
    "age": "有",
    "quyu": "2019",
    "": "二七-万客来",
    "shoufu": "",
    "xiaoqu": "郑州绿地城",
    "position": 4
  },
  {
    "id": "2510147273",
    "area": "120",
    "feature": "满五",
    "title": "二七新城 绿地开发 南北通透三房 精装交付 可以低首付",
    "xiaoqu_": "郑州绿地城",
    "room": "3室2厅",
    "total_price": "140",
    "url": "http://m.fang.com/esf/zz/JHAGT_180849896_17652212x2510147273_166441564.html",
    "price": "11667元/㎡ ",
    "louceng": "低层/33层",
    "louxing": "板楼",
    "chaoxiang": "南",
    "zhuangxiu": "精装修",
    "age": "2018",
    "quyu": "二七-万客来",
    "shoufu": "",
    "xiaoqu": "郑州绿地城",
    "position": 5
  },
  {
    "id": "2510147273",
    "area": "109",
    "feature": "满五",
    "title": "世界 500强企业绿地开发 均价12500精装修交房，",
    "xiaoqu_": "郑州绿地城",
    "room": "3室2厅",
    "total_price": "130",
    "url": "http://m.fang.com/esf/zz/JHAGT_180852904_17654577x2510147273_166702818.html",
    "price": "11927元/㎡ ",
    "louceng": "中层/33层",
    "louxing": "板楼",
    "chaoxiang": "南",
    "zhuangxiu": "精装修",
    "age": "有",
    "quyu": "2014",
    "": "二七-万客来",
    "shoufu": "",
    "xiaoqu": "郑州绿地城",
    "position": 6
  },
  {
    "id": "2510147273",
    "area": "89",
    "feature": "",
    "title": "南三环华侨城旁，绿地城，均价12XXX，首付可分期，精装交付",
    "xiaoqu_": "郑州绿地城",
    "room": "3室2厅",
    "total_price": "110",
    "url": "http://m.fang.com/esf/zz/JHAGT_180125400_11287939x2510147273_166627417.html",
    "price": "12360元/㎡ ",
    "louceng": "中层/31层",
    "louxing": "板楼",
    "chaoxiang": "南",
    "zhuangxiu": "精装修",
    "age": "有",
    "quyu": "2019",
    "": "二七-万客来",
    "shoufu": "",
    "xiaoqu": "郑州绿地城",
    "position": 7
  },
  {
    "id": "2510147273",
    "area": "142",
    "feature": "满五",
    "title": "南三环 嵩山路 绿地大开发商精装双气交房，特价急售",
    "xiaoqu_": "郑州绿地城",
    "room": "4室2厅",
    "total_price": "160",
    "url": "http://m.fang.com/esf/zz/JHAGT_180852896_17654571x2510147273_166702818.html",
    "price": "11268元/㎡ ",
    "louceng": "中层/34层",
    "louxing": "板楼",
    "chaoxiang": "东南",
    "zhuangxiu": "精装修",
    "age": "有",
    "quyu": "2020",
    "": "二七-万客来",
    "shoufu": "",
    "xiaoqu": "郑州绿地城",
    "position": 8
  },
  {
    "id": "2510147273",
    "area": "125",
    "feature": "",
    "title": "南三环 1000亩大盘 单价11400买125平精装大三房",
    "xiaoqu_": "郑州绿地城",
    "room": "3室2厅",
    "total_price": "143",
    "url": "http://m.fang.com/esf/zz/JHAGT_180852546_17654173x2510147273_166788757.html",
    "price": "11440元/㎡ ",
    "louceng": "高层/28层",
    "louxing": "南北",
    "chaoxiang": "精装修",
    "zhuangxiu": "有",
    "age": "有",
    "quyu": "2020",
    "": "二七-万客来",
    "shoufu": "",
    "xiaoqu": "郑州绿地城",
    "position": 9
  },
  {
    "id": "2510147273",
    "area": "140",
    "feature": "满五",
    "title": "南三环郑密路 郑州绿地城 大开发商 16个地点 精装交房",
    "xiaoqu_": "郑州绿地城",
    "room": "4室2厅",
    "total_price": "160",
    "url": "http://m.fang.com/esf/zz/JHAGT_180855339_16268131x2510147273_166549447.html",
    "price": "11429元/㎡ ",
    "louceng": "低层/20层",
    "louxing": "板楼",
    "chaoxiang": "南",
    "zhuangxiu": "精装修",
    "age": "2019",
    "quyu": "二七-万客来",
    "shoufu": "",
    "xiaoqu": "郑州绿地城",
    "position": 10
  },
  {
    "id": "2510147273",
    "area": "140",
    "feature": "满二",
    "title": "郑州绿地城 精装修双气 千亩大盘 幼儿园都有 首付分期",
    "xiaoqu_": "郑州绿地城",
    "room": "4室2厅",
    "total_price": "145",
    "url": "http://m.fang.com/esf/zz/JHAGT_175543716_14144612x2510147273_164963281.html",
    "price": "10357元/㎡ ",
    "louceng": "中层/20层",
    "louxing": "板楼",
    "chaoxiang": "南",
    "zhuangxiu": "精装修",
    "age": "有",
    "quyu": "有",
    "": "二七-万客来",
    "shoufu": "",
    "xiaoqu": "郑州绿地城",
    "position": 11
  },
  {
    "id": "2510147273",
    "area": "138",
    "feature": "",
    "title": "业主出国急售直降40万绿地城 精装双气四房",
    "xiaoqu_": "郑州绿地城",
    "room": "4室2厅",
    "total_price": "143",
    "url": "http://m.fang.com/esf/zz/JHAGT_180694371_17466537x2510147273_166787463.html",
    "price": "10362元/㎡ ",
    "louceng": "中层/27层",
    "louxing": "塔楼",
    "chaoxiang": "南北",
    "zhuangxiu": "精装修",
    "age": "有",
    "quyu": "有",
    "": "二七-万客来",
    "shoufu": "",
    "xiaoqu": "郑州绿地城",
    "position": 12
  },
  {
    "id": "2510147273",
    "area": "88",
    "feature": "满五",
    "title": "（真） 绿地开发 八层洋房公寓 精装修双气住宅 南北通透",
    "xiaoqu_": "郑州绿地城",
    "room": "3室2厅",
    "total_price": "105",
    "url": "http://m.fang.com/esf/zz/JHAGT_180844564_17667507x2510147273_166813153.html",
    "price": "11932元/㎡ ",
    "louceng": "高层/27层",
    "louxing": "塔楼",
    "chaoxiang": "南",
    "zhuangxiu": "精装修",
    "age": "有",
    "quyu": "有",
    "": "二七-万客来",
    "shoufu": "",
    "xiaoqu": "郑州绿地城",
    "position": 13
  },
  {
    "id": "2510147273",
    "area": "100",
    "feature": "满五",
    "title": "南三环 郑州华侨城千大盘 7400文旅项目三带五园九",
    "xiaoqu_": "郑州绿地城",
    "room": "3室2厅",
    "total_price": "130",
    "url": "http://m.fang.com/esf/zz/JHAGT_180854744_16885955x2510147273_166379476.html",
    "price": "13000元/㎡ ",
    "louceng": "低层/30层",
    "louxing": "板楼",
    "chaoxiang": "南北",
    "zhuangxiu": "毛坯",
    "age": "有",
    "quyu": "2019",
    "": "二七-万客来",
    "shoufu": "",
    "xiaoqu": "郑州绿地城",
    "position": 14
  },
  {
    "id": "2510147273",
    "area": "120",
    "feature": "满五",
    "title": "（真）南三环运河畔 千亩大盘 绿地开发 高绿化 精装修",
    "xiaoqu_": "郑州绿地城",
    "room": "3室2厅",
    "total_price": "144",
    "url": "http://m.fang.com/esf/zz/JHAGT_180853698_13522943x2510147273_165305460.html",
    "price": "12000元/㎡ ",
    "louceng": "中层/27层",
    "louxing": "板楼",
    "chaoxiang": "南北",
    "zhuangxiu": "精装修",
    "age": "有",
    "quyu": "2019",
    "": "二七-万客来",
    "shoufu": "郑州绿地城",
    "xiaoqu": null,
    "position": 15
  },
  {
    "id": "2510147273",
    "area": "90",
    "feature": "",
    "title": "团购渠道.绿地城，二七新区千亩大盘，精装1.1万起.品牌地产",
    "xiaoqu_": "郑州绿地城",
    "room": "3室2厅",
    "total_price": "108",
    "url": "http://m.fang.com/esf/zz/JHAGT_180851711_17442154x2510147273_166001762.html",
    "price": "12000元/㎡ ",
    "louceng": "低层/34层",
    "louxing": "板楼",
    "chaoxiang": "南北",
    "zhuangxiu": "精装修",
    "age": "有",
    "quyu": "2018",
    "": "二七-万客来",
    "shoufu": "",
    "xiaoqu": "郑州绿地城",
    "position": 16
  },
  {
    "id": "2510147273",
    "area": "89",
    "feature": "满二",
    "title": "郑州绿地城 精装修 首付可分期 一年不用还月供 可更名挣差价",
    "xiaoqu_": "郑州绿地城",
    "room": "3室2厅",
    "total_price": "90",
    "url": "http://m.fang.com/esf/zz/JHAGT_175836632_11284641x2510147273_164963281.html",
    "price": "10112元/㎡ ",
    "louceng": "高层/27层",
    "louxing": "板楼",
    "chaoxiang": "南",
    "zhuangxiu": "精装修",
    "age": "有",
    "quyu": "有",
    "": "二七-万客来",
    "shoufu": "",
    "xiaoqu": "郑州绿地城",
    "position": 17
  },
  {
    "id": "2510147273",
    "area": "122",
    "feature": "满二",
    "title": "南三环绿地城 5万网签 精装交房 单价1.13万 看房车接车送",
    "xiaoqu_": "郑州绿地城",
    "room": "3室2厅",
    "total_price": "135",
    "url": "http://m.fang.com/esf/zz/JHAGT_180848224_17650746x2510147273_166804531.html",
    "price": "11066元/㎡ ",
    "louceng": "中层/33层",
    "louxing": "平房",
    "chaoxiang": "南北",
    "zhuangxiu": "精装修",
    "age": "有",
    "quyu": "有",
    "": "二七-万客来",
    "shoufu": "",
    "xiaoqu": "郑州绿地城",
    "position": 18
  },
  {
    "id": "2510147273",
    "area": "110",
    "feature": "满五",
    "title": "南三环绿地，精装修，均价12000，千亩大盘，南北通透",
    "xiaoqu_": "郑州绿地城",
    "room": "3室2厅",
    "total_price": "143",
    "url": "http://m.fang.com/esf/zz/JHAGT_180360761_17205416x2510147273_166725764.html",
    "price": "13000元/㎡ ",
    "louceng": "中层/30层",
    "louxing": "板楼",
    "chaoxiang": "南北",
    "zhuangxiu": "精装修",
    "age": "有",
    "quyu": "2014",
    "": "二七-万客来",
    "shoufu": "",
    "xiaoqu": "郑州绿地城",
    "position": 19
  },
  {
    "id": "2510147273",
    "area": "120",
    "feature": "满五",
    "title": "绿地开发 南三环千亩大盘 送精装修 均价11000 地铁口",
    "xiaoqu_": "郑州绿地城",
    "room": "3室2厅",
    "total_price": "130",
    "url": "http://m.fang.com/esf/zz/JHAGT_180851802_16601434x2510147273_166201298.html",
    "price": "10833元/㎡ ",
    "louceng": "高层/26层",
    "louxing": "板楼",
    "chaoxiang": "南北",
    "zhuangxiu": "精装修",
    "age": "有",
    "quyu": "2017",
    "": "二七-万客来",
    "shoufu": "",
    "xiaoqu": "郑州绿地城",
    "position": 20
  }
]