[
  {
    "id": "2510434355",
    "area": "102",
    "feature": "满五",
    "title": "户型格局好 视野开阔，采光充足。 业主诚心出售",
    "xiaoqu_": "帆布厂家属院",
    "room": "3室2厅",
    "total_price": "122",
    "price": "11961元/㎡ ",
    "louceng": "高层/7层",
    "louxing": "板楼",
    "chaoxiang": "西南",
    "zhuangxiu": "中装修",
    "age": "1994",
    "quyu": "管城-二里岗",
    "shoufu": "",
    "xiaoqu": "帆布厂家属院",
    "position": 1
  },
  {
    "id": "2510434355",
    "area": "115.1",
    "feature": "满五",
    "title": "帆布厂家属院 大三居 低层 创新街 地铁二号线 随时看",
    "xiaoqu_": "帆布厂家属院",
    "room": "3室1厅",
    "total_price": "140",
    "price": "12163元/㎡ ",
    "louceng": "中层/6层",
    "louxing": "板楼",
    "chaoxiang": "南北",
    "zhuangxiu": "精装修",
    "age": "2003",
    "quyu": "管城-二里岗",
    "shoufu": "约61.2万，月供4590元",
    "xiaoqu": "帆布厂家属院",
    "position": 2
  },
  {
    "id": "2510434355",
    "area": "81",
    "feature": "满五",
    "title": "多层3楼 户型格局好 视野开阔，采光充足 业主诚心出售",
    "xiaoqu_": "帆布厂家属院",
    "room": "2室1厅",
    "total_price": "105",
    "price": "12963元/㎡ ",
    "louceng": "中层/7层",
    "louxing": "板楼",
    "chaoxiang": "南",
    "zhuangxiu": "中装修",
    "age": "1994",
    "quyu": "管城-二里岗",
    "shoufu": "",
    "xiaoqu": "帆布厂家属院",
    "position": 3
  }
]