[
  {
    "id": "2510753289",
    "area": "124.27",
    "feature": "",
    "title": "CBD旁宏光协和城邦双气夜景观郑东",
    "xiaoqu_": "宏光协和城邦",
    "room": "3室2厅",
    "total_price": "225",
    "price": "18106元/㎡ ",
    "louceng": "低层/20层",
    "louxing": "板楼",
    "chaoxiang": "南北",
    "zhuangxiu": "简装修",
    "age": "2013",
    "quyu": "金水-未来大厦",
    "shoufu": "约98.7万，月供7355元",
    "xiaoqu": "宏光协和城邦",
    "position": 1
  },
  {
    "id": "2510753289",
    "area": "135",
    "feature": "满五",
    "title": "近地铁口 南北通透 精装三房 拎包入住",
    "xiaoqu_": "宏光协和城邦",
    "room": "3室2厅",
    "total_price": "220",
    "price": "16296元/㎡ ",
    "louceng": "高层/32层",
    "louxing": "板楼",
    "chaoxiang": "南北",
    "zhuangxiu": "精装修",
    "age": "有",
    "quyu": "2015",
    "": "金水-未来大厦",
    "shoufu": "约96.4万，月供7199元",
    "xiaoqu": "宏光协和城邦",
    "position": 2
  }
]