[
  {
    "id": "2510148421",
    "area": "123.7",
    "feature": "满五",
    "title": "腾威城 9万网签 金二环 CBD旁 三地铁环绕 康桥物业 郑",
    "xiaoqu_": "腾威城",
    "room": "3室2厅",
    "total_price": "225",
    "url": "http://m.fang.com/esf/zz/JHAGT_180238240_16854917x2510148421_166627417.html",
    "price": "18189元/㎡ ",
    "louceng": "低层/30层",
    "louxing": "板楼",
    "chaoxiang": "南",
    "zhuangxiu": "毛坯",
    "age": "有",
    "quyu": "有",
    "": "金水-东建材",
    "shoufu": "",
    "xiaoqu": "腾威城",
    "position": 1
  },
  {
    "id": "2510148421",
    "area": "116",
    "feature": "",
    "title": "腾威城双地铁口全对望CBD经济中心团购价",
    "xiaoqu_": "腾威城",
    "room": "3室2厅",
    "total_price": "185",
    "url": "http://m.fang.com/esf/zz/JHAGT_180707401_17460545x2510148421_166547766.html",
    "price": "15948元/㎡ ",
    "louceng": "低层/33层",
    "louxing": "板楼",
    "chaoxiang": "南北",
    "zhuangxiu": "毛坯",
    "age": "有",
    "quyu": "2015",
    "": "金水-东建材",
    "shoufu": "",
    "xiaoqu": "腾威城",
    "position": 2
  },
  {
    "id": "2510148421",
    "area": "116",
    "feature": "满二",
    "title": "东建材新楼盘 地铁口100米 清盘钜惠",
    "xiaoqu_": "腾威城",
    "room": "3室2厅",
    "total_price": "190",
    "url": "http://m.fang.com/esf/zz/JHAGT_180737559_17523134x2510148421_166631289.html",
    "price": "16379元/㎡ ",
    "louceng": "中层/25层",
    "louxing": "南北",
    "chaoxiang": "毛坯",
    "zhuangxiu": "有",
    "age": "有",
    "quyu": "金水-东建材",
    "shoufu": "腾威城",
    "xiaoqu": null,
    "position": 3
  },
  {
    "id": "2510148421",
    "area": "92",
    "feature": "",
    "title": "中州大道郑汴路东建材双地铁口康桥物业，改善",
    "xiaoqu_": "腾威城",
    "room": "2室2厅",
    "total_price": "165",
    "url": "http://m.fang.com/esf/zz/JHAGT_180692334_17049151x2510148421_160402658.html",
    "price": "17935元/㎡ ",
    "louceng": "中层/32层",
    "louxing": "板楼",
    "chaoxiang": "南",
    "zhuangxiu": "精装修",
    "age": "有",
    "quyu": "2015",
    "": "金水-东建材",
    "shoufu": "",
    "xiaoqu": "腾威城",
    "position": 4
  },
  {
    "id": "2510148421",
    "area": "124",
    "feature": "",
    "title": "郑汴路英协路 腾威城 舒适三房 康桥物业",
    "xiaoqu_": "腾威城",
    "room": "3室2厅",
    "total_price": "225",
    "url": "http://m.fang.com/esf/zz/JHAGT_180205838_17050277x2510148421_166441564.html",
    "price": "18145元/㎡ ",
    "louceng": "中层/33层",
    "louxing": "塔板结合",
    "chaoxiang": "南北",
    "zhuangxiu": "毛坯",
    "age": "有",
    "quyu": "有",
    "": "金水-东建材",
    "shoufu": "腾威城",
    "xiaoqu": null,
    "position": 5
  },
  {
    "id": "2510148421",
    "area": "96",
    "feature": "",
    "title": "新房团购，升龙凤凰城旁，三口，腾威城，小高层，市",
    "xiaoqu_": "腾威城",
    "room": "2室2厅",
    "total_price": "170",
    "url": "http://m.fang.com/esf/zz/JHAGT_180720132_17497103x2510148421_166182936.html",
    "price": "17708元/㎡ ",
    "louceng": "中层/30层",
    "louxing": "板楼",
    "chaoxiang": "南",
    "zhuangxiu": "毛坯",
    "age": "有",
    "quyu": "2019",
    "": "金水-东建材",
    "shoufu": "",
    "xiaoqu": "腾威城",
    "position": 6
  },
  {
    "id": "2510148421",
    "area": "95",
    "feature": "满五",
    "title": "中州大道腾威城 9万订房 2年付首付 新房 金二环 地铁",
    "xiaoqu_": "腾威城",
    "room": "3室2厅",
    "total_price": "162",
    "url": "http://m.fang.com/esf/zz/JHAGT_180709548_17485312x2510148421_166623807.html",
    "price": "17053元/㎡ ",
    "louceng": "高层/29层",
    "louxing": "板楼",
    "chaoxiang": "南",
    "zhuangxiu": "精装修",
    "age": "有",
    "quyu": "2020",
    "": "金水-东建材",
    "shoufu": "",
    "xiaoqu": "腾威城",
    "position": 7
  },
  {
    "id": "2510148421",
    "area": "123",
    "feature": "满五",
    "title": "三地铁环绕 腾威城 小高层 升龙凤凰城旁 首付可分期",
    "xiaoqu_": "腾威城",
    "room": "3室2厅",
    "total_price": "210",
    "url": "http://m.fang.com/esf/zz/JHAGT_180739898_17047441x2510148421_166733291.html",
    "price": "17073元/㎡ ",
    "louceng": "高层/33层",
    "louxing": "板楼",
    "chaoxiang": "南北",
    "zhuangxiu": "中装修",
    "age": "有",
    "quyu": "有",
    "": "金水-东建材",
    "shoufu": "",
    "xiaoqu": "腾威城",
    "position": 8
  },
  {
    "id": "2510148421",
    "area": "91",
    "feature": "满五",
    "title": "三地铁环绕 核心价值低谷 品质物业",
    "xiaoqu_": "腾威城",
    "room": "2室2厅",
    "total_price": "168",
    "url": "http://m.fang.com/esf/zz/JHAGT_180695427_17468009x2510148421_166723571.html",
    "price": "18462元/㎡ ",
    "louceng": "中层/22层",
    "louxing": "塔楼",
    "chaoxiang": "南北",
    "zhuangxiu": "精装修",
    "age": "有",
    "quyu": "有",
    "": "金水-东建材",
    "shoufu": "腾威城",
    "xiaoqu": null,
    "position": 9
  },
  {
    "id": "2510148421",
    "area": "96",
    "feature": "",
    "title": "CBD旁 金二环 腾威城 三环绕配套齐全 康桥物业",
    "xiaoqu_": "腾威城",
    "room": "3室2厅",
    "total_price": "146",
    "url": "http://m.fang.com/esf/zz/JHAGT_180723086_17500968x2510148421_166014398.html",
    "price": "15208元/㎡ ",
    "louceng": "低层/30层",
    "louxing": "板楼",
    "chaoxiang": "南",
    "zhuangxiu": "毛坯",
    "age": "有",
    "quyu": "2017",
    "": "金水-东建材",
    "shoufu": "",
    "xiaoqu": "腾威城",
    "position": 10
  },
  {
    "id": "2510148421",
    "area": "97",
    "feature": "",
    "title": "东二环内 三地铁口环绕 郑州核心区位 9万网签国家一级康桥物",
    "xiaoqu_": "腾威城",
    "room": "3室2厅",
    "total_price": "150",
    "url": "http://m.fang.com/esf/zz/JHAGT_180181181_16793066x2510148421_166610219.html",
    "price": "15464元/㎡ ",
    "louceng": "中层/17层",
    "louxing": "板楼",
    "chaoxiang": "南",
    "zhuangxiu": "精装修",
    "age": "有",
    "quyu": "2018",
    "": "金水-东建材",
    "shoufu": "",
    "xiaoqu": "腾威城",
    "position": 11
  },
  {
    "id": "2510148421",
    "area": "93",
    "feature": "",
    "title": "郑汴路英协路 腾威城 南向两房 康桥物业",
    "xiaoqu_": "腾威城",
    "room": "2室1厅",
    "total_price": "160",
    "url": "http://m.fang.com/esf/zz/JHAGT_180205797_17050199x2510148421_166441564.html",
    "price": "17204元/㎡ ",
    "louceng": "中层/33层",
    "louxing": "塔板结合",
    "chaoxiang": "南北",
    "zhuangxiu": "毛坯",
    "age": "有",
    "quyu": "有",
    "": "金水-东建材",
    "shoufu": "腾威城",
    "xiaoqu": null,
    "position": 12
  },
  {
    "id": "2510148421",
    "area": "96",
    "feature": "满五",
    "title": "升龙凤凰城旁，三地铁口，腾威城，，找我更优惠",
    "xiaoqu_": "腾威城",
    "room": "2室2厅",
    "total_price": "166",
    "url": "http://m.fang.com/esf/zz/JHAGT_180717989_17494885x2510148421_166628325.html",
    "price": "17292元/㎡ ",
    "louceng": "高层/30层",
    "louxing": "板楼",
    "chaoxiang": "南",
    "zhuangxiu": "毛坯",
    "age": "有",
    "quyu": "2019",
    "": "金水-东建材",
    "shoufu": "腾威城",
    "xiaoqu": null,
    "position": 13
  },
  {
    "id": "2510148421",
    "area": "90",
    "feature": "满五",
    "title": "就是公园，开车5到大玉米，二环难得的好地方，给力",
    "xiaoqu_": "腾威城",
    "room": "3室2厅",
    "total_price": "162",
    "url": "http://m.fang.com/esf/zz/JHAGT_180739897_17229968x2510148421_166733291.html",
    "price": "18000元/㎡ ",
    "louceng": "高层/32层",
    "louxing": "板楼",
    "chaoxiang": "南",
    "zhuangxiu": "中装修",
    "age": "有",
    "quyu": "有",
    "": "金水-东建材",
    "shoufu": "",
    "xiaoqu": "腾威城",
    "position": 14
  },
  {
    "id": "2510148421",
    "area": "136",
    "feature": "配套成熟",
    "title": "CBD旁 金二环 三地 铁环绕 配套齐全 户型任选 优惠中",
    "xiaoqu_": "腾威城",
    "room": "3室2厅",
    "total_price": "251",
    "url": "http://m.fang.com/esf/zz/JHAGT_180727690_17485303x2510148421_160589339.html",
    "price": "18456元/㎡ ",
    "louceng": "中层/32层",
    "louxing": "板楼",
    "chaoxiang": "南北",
    "zhuangxiu": "毛坯",
    "age": "有",
    "quyu": "有",
    "": "金水-东建材",
    "shoufu": "",
    "xiaoqu": "腾威城",
    "position": 15
  },
  {
    "id": "2510148421",
    "area": "89",
    "feature": "配套成熟",
    "title": "二环内 三条地 铁线 CBD为临 改善盘 满足十二年",
    "xiaoqu_": "腾威城",
    "room": "3室2厅",
    "total_price": "155",
    "url": "http://m.fang.com/esf/zz/JHAGT_180723432_17485308x2510148421_160589339.html",
    "price": "17416元/㎡ ",
    "louceng": "高层/33层",
    "louxing": "板楼",
    "chaoxiang": "南",
    "zhuangxiu": "毛坯",
    "age": "有",
    "quyu": "有",
    "": "金水-东建材",
    "shoufu": "",
    "xiaoqu": "腾威城",
    "position": 16
  },
  {
    "id": "2510148421",
    "area": "118",
    "feature": "满五",
    "title": "康桥品质 媲美永威 渠道购房 优惠更大",
    "xiaoqu_": "腾威城",
    "room": "3室2厅",
    "total_price": "210",
    "url": "http://m.fang.com/esf/zz/JHAGT_180701821_17475373x2510148421_166723571.html",
    "price": "17797元/㎡ ",
    "louceng": "中层/26层",
    "louxing": "塔楼",
    "chaoxiang": "南北",
    "zhuangxiu": "精装修",
    "age": "有",
    "quyu": "有",
    "": "金水-东建材",
    "shoufu": "腾威城",
    "xiaoqu": null,
    "position": 17
  },
  {
    "id": "2510148421",
    "area": "93",
    "feature": "满五",
    "title": "3地铁交汇 地理位置优越 商业配套完善 康桥物业 对望郑东CBD",
    "xiaoqu_": "腾威城",
    "room": "2室2厅",
    "total_price": "172",
    "url": "http://m.fang.com/esf/zz/JHAGT_180857944_17039312x2510148421_166555272.html",
    "price": "18495元/㎡ ",
    "louceng": "高层/17层",
    "louxing": "板楼",
    "chaoxiang": "南",
    "zhuangxiu": "毛坯",
    "age": "有",
    "quyu": "2020",
    "": "金水-东建材",
    "shoufu": "",
    "xiaoqu": "腾威城",
    "position": 18
  },
  {
    "id": "2510148421",
    "area": "153",
    "feature": "",
    "title": "CBD旁 金二环 腾威城 三地铁环绕配套齐全 康桥物业",
    "xiaoqu_": "腾威城",
    "room": "4室2厅",
    "total_price": "245",
    "url": "http://m.fang.com/esf/zz/JHAGT_180100003_16943545x2510148421_166021682.html",
    "price": "16013元/㎡ ",
    "louceng": "中层/32层",
    "louxing": "钢混",
    "chaoxiang": "南北",
    "zhuangxiu": "毛坯",
    "age": "有",
    "quyu": "有",
    "": "金水-东建材",
    "shoufu": "腾威城",
    "xiaoqu": null,
    "position": 19
  }
]