[
  {
    "id": "2510473881",
    "area": "76",
    "feature": "满五",
    "title": "黄河北街4号院（均价9千多，全明两室）户型带劲，采光好，",
    "xiaoqu_": "黄河北街10号院",
    "room": "2室2厅",
    "total_price": "76",
    "url": "http://m.fang.com/esf/zz/JHAGT_180800842_17555006x2510473881_165263196.html",
    "price": "10000元/㎡ ",
    "louceng": "中层/7层",
    "louxing": "板楼",
    "chaoxiang": "南",
    "zhuangxiu": "精装修",
    "age": "2000",
    "quyu": "金水-水上乐园",
    "shoufu": "",
    "xiaoqu": "黄河北街10号院",
    "position": 1
  }
]