[
  {
    "id": "2510661901",
    "area": "105",
    "feature": "满五",
    "title": "出售 裕达别墅小洋房 中间楼层 南北通透 沐浴阳光一整天",
    "xiaoqu_": "裕达别墅",
    "room": "3室2厅",
    "total_price": "100",
    "price": "9524元/㎡ ",
    "louceng": "高层/7层",
    "louxing": "板楼",
    "chaoxiang": "东西",
    "zhuangxiu": "简装修",
    "age": "有",
    "quyu": "1995",
    "": "二七-老郑大",
    "shoufu": "约52.5万，月供2817元",
    "xiaoqu": "裕达别墅",
    "position": 1
  },
  {
    "id": "2510661901",
    "area": "92",
    "feature": "满五",
    "title": "三附院隔壁，裕达别墅，中间楼层三房，看房方便",
    "xiaoqu_": "裕达别墅",
    "room": "2室2厅",
    "total_price": "107",
    "price": "11630元/㎡ ",
    "louceng": "中层/7层",
    "louxing": "板楼",
    "chaoxiang": "东西",
    "zhuangxiu": "精装修",
    "age": "1996",
    "quyu": "二七-老郑大",
    "shoufu": "约57万，月供2973元",
    "xiaoqu": "裕达别墅",
    "position": 2
  }
]