[
  {
    "id": "2510468081",
    "area": "100",
    "feature": "满五",
    "title": "急售，郑师，均价1万首付18万全明三室，近公园，无税",
    "xiaoqu_": "杜岭街人民路小区",
    "room": "3室2厅",
    "total_price": "105",
    "url": "http://m.fang.com/esf/zz/JHAGT_180825747_17632574x2510468081_163566161.html",
    "price": "10500元/㎡ ",
    "louceng": "中层/7层",
    "louxing": "板楼",
    "chaoxiang": "南北",
    "zhuangxiu": "精装修",
    "age": "有",
    "quyu": "有",
    "": "金水-紫荆山",
    "shoufu": "",
    "xiaoqu": "杜岭街人民路小区",
    "position": 1
  },
  {
    "id": "2510468081",
    "area": "67",
    "feature": "满五",
    "title": "杜岭街西里路 3楼 全明两房 出门公园 上郑师 房东诚心卖",
    "xiaoqu_": "杜岭街人民路小区",
    "room": "2室1厅",
    "total_price": "64",
    "url": "http://m.fang.com/esf/zz/JHAGT_180737236_17188774x2510468081_164331581.html",
    "price": "9552元/㎡ ",
    "louceng": "中层/7层",
    "louxing": "塔板结合",
    "chaoxiang": "南北",
    "zhuangxiu": "中装修",
    "age": "有",
    "quyu": "有",
    "": "金水-紫荆山",
    "shoufu": "",
    "xiaoqu": "杜岭街人民路小区",
    "position": 2
  },
  {
    "id": "2510468081",
    "area": "93",
    "feature": "满五",
    "title": "丹尼斯大卫城（均价一万，精装三居室）楼层好，户型好，出价就谈",
    "xiaoqu_": "杜岭街人民路小区",
    "room": "3室1厅",
    "total_price": "93",
    "url": "http://m.fang.com/esf/zz/JHAGT_180786817_11294815x2510468081_163378952.html",
    "price": "10000元/㎡ ",
    "louceng": "中层/7层",
    "louxing": "南北",
    "chaoxiang": "精装修",
    "zhuangxiu": "1998",
    "age": "金水-紫荆山",
    "shoufu": "",
    "xiaoqu": "杜岭街人民路小区",
    "position": 3
  },
  {
    "id": "2510468081",
    "area": "90",
    "feature": "满五",
    "title": "杜岭街西里路 3楼通透三房，上郑师 地铁口丹尼斯 ，看房方便",
    "xiaoqu_": "杜岭街人民路小区",
    "room": "3室1厅",
    "total_price": "90",
    "url": "http://m.fang.com/esf/zz/JHAGT_180797260_17602391x2510468081_164331581.html",
    "price": "10000元/㎡ ",
    "louceng": "中层/7层",
    "louxing": "塔板结合",
    "chaoxiang": "南北",
    "zhuangxiu": "中装修",
    "age": "有",
    "quyu": "有",
    "": "金水-紫荆山",
    "shoufu": "",
    "xiaoqu": "杜岭街人民路小区",
    "position": 4
  }
]