[
  {
    "id": "2510236545",
    "area": "164",
    "feature": "满五",
    "title": "二环之内，生活设施齐全，位置优越",
    "xiaoqu_": "绿城黄河锦园",
    "room": "3室2厅",
    "total_price": "210",
    "url": "http://m.fang.com/esf/zz/JHAGT_180842086_17298658x2510236545_166803205.html",
    "price": "12805元/㎡ ",
    "louceng": "中层/16层",
    "louxing": "板楼",
    "chaoxiang": "北",
    "zhuangxiu": "简装修",
    "age": "有",
    "quyu": "2012",
    "": "金水-大石桥",
    "shoufu": "",
    "xiaoqu": "绿城黄河锦园",
    "position": 1
  },
  {
    "id": "2510236545",
    "area": "165",
    "feature": "满五",
    "title": "均价一万市五院 黄河锦园精装双气3室2厅 温馨舒适 急售 随时看房",
    "xiaoqu_": "绿城黄河锦园",
    "room": "3室2厅",
    "total_price": "175",
    "url": "http://m.fang.com/esf/zz/JHAGT_180351658_17067440x2510236545_166649012.html",
    "price": "10606元/㎡ ",
    "louceng": "中层/18层",
    "louxing": "钢混",
    "chaoxiang": "南",
    "zhuangxiu": "精装修",
    "age": "2003",
    "quyu": "金水-大石桥",
    "shoufu": "",
    "xiaoqu": "绿城黄河锦园",
    "position": 2
  },
  {
    "id": "2510236545",
    "area": "166",
    "feature": "满五",
    "title": "均价1万买电梯3房双厅双卫 地铁口 室内使用面积大 采光好",
    "xiaoqu_": "绿城黄河锦园",
    "room": "3室2厅",
    "total_price": "169",
    "url": "http://m.fang.com/esf/zz/JHAGT_180791363_17592559x2510236545_166520430.html",
    "price": "10181元/㎡ ",
    "louceng": "高层/16层",
    "louxing": "板楼",
    "chaoxiang": "南北",
    "zhuangxiu": "精装修",
    "age": "有",
    "quyu": "2003",
    "": "金水-大石桥",
    "shoufu": "",
    "xiaoqu": "绿城黄河锦园",
    "position": 3
  },
  {
    "id": "2510236545",
    "area": "164",
    "feature": "满五",
    "title": "绿城mini国际 南北通透大三房 采光好 诚心出售",
    "xiaoqu_": "绿城黄河锦园",
    "room": "3室2厅",
    "total_price": "177",
    "url": "http://m.fang.com/esf/zz/JHAGT_180842019_17645366x2510236545_166803205.html",
    "price": "10793元/㎡ ",
    "louceng": "高层/16层",
    "louxing": "板楼",
    "chaoxiang": "南北",
    "zhuangxiu": "简装修",
    "age": "有",
    "quyu": "2012",
    "": "金水-大石桥",
    "shoufu": "",
    "xiaoqu": "绿城黄河锦园",
    "position": 4
  },
  {
    "id": "2510236545",
    "area": "55",
    "feature": "满五",
    "title": "此房满五年，年代新精装双气电梯房。地理位置好",
    "xiaoqu_": "绿城黄河锦园",
    "room": "1室0厅",
    "total_price": "90",
    "url": "http://m.fang.com/esf/zz/JHAGT_180842068_17645388x2510236545_166803205.html",
    "price": "16364元/㎡ ",
    "louceng": "中层/25层",
    "louxing": "板楼",
    "chaoxiang": "北",
    "zhuangxiu": "中装修",
    "age": "有",
    "quyu": "2008",
    "": "金水-大石桥",
    "shoufu": "",
    "xiaoqu": "绿城黄河锦园",
    "position": 5
  },
  {
    "id": "2510236545",
    "area": "41.85",
    "feature": "满五",
    "title": "环城双地铁线 真正的精装修 房东诚意卖 满五",
    "xiaoqu_": "绿城黄河锦园",
    "room": "1室0厅",
    "total_price": "72",
    "url": "http://m.fang.com/esf/zz/JHAGT_180842008_17261855x2510236545_166803205.html",
    "price": "17204元/㎡ ",
    "louceng": "高层/25层",
    "louxing": "板楼",
    "chaoxiang": "南北",
    "zhuangxiu": "精装修",
    "age": "有",
    "quyu": "2015",
    "": "金水-大石桥",
    "shoufu": "",
    "xiaoqu": "绿城黄河锦园",
    "position": 6
  },
  {
    "id": "2510236545",
    "area": "165",
    "feature": "满五",
    "title": "业主急急急售，急急急急，真真真！",
    "xiaoqu_": "绿城黄河锦园",
    "room": "4室2厅",
    "total_price": "160",
    "url": "http://m.fang.com/esf/zz/JHAGT_180844924_17611827x2510236545_166684816.html",
    "price": "9697元/㎡ ",
    "louceng": "高层/16层",
    "louxing": "钢混",
    "chaoxiang": "南北",
    "zhuangxiu": "精装修",
    "age": "有",
    "quyu": "有",
    "": "金水-大石桥",
    "shoufu": "",
    "xiaoqu": "绿城黄河锦园",
    "position": 7
  }
]