[
  {
    "id": "2510466269",
    "area": "68",
    "feature": "满五",
    "title": "文化路红旗路（五院家属院，双气三楼）全明两室，首付15万，真",
    "xiaoqu_": "五院家属院",
    "room": "2室2厅",
    "total_price": "75",
    "url": "http://m.fang.com/esf/zz/JHAGT_180800724_17539009x2510466269_165263196.html",
    "price": "11029元/㎡ ",
    "louceng": "中层/7层",
    "louxing": "板楼",
    "chaoxiang": "南",
    "zhuangxiu": "精装修",
    "age": "1999",
    "quyu": "金水-水上乐园",
    "shoufu": "",
    "xiaoqu": "五院家属院",
    "position": 1
  },
  {
    "id": "2510466269",
    "area": "73.62",
    "feature": "满五",
    "title": "五院家属院 双气社区 首付20万 非顶楼 全明2房 上 文化路2小。。",
    "xiaoqu_": "五院家属院",
    "room": "2室2厅",
    "total_price": "78",
    "url": "http://m.fang.com/esf/zz/JHAGT_180795566_17568683x2510466269_163973456.html",
    "price": "10595元/㎡ ",
    "louceng": "中层/8层",
    "louxing": "板楼",
    "chaoxiang": "南北",
    "zhuangxiu": "精装修",
    "age": "2000",
    "quyu": "金水-水上乐园",
    "shoufu": "",
    "xiaoqu": "五院家属院",
    "position": 2
  },
  {
    "id": "2510466269",
    "area": "102.2",
    "feature": "满五",
    "title": "新出五院家属院 双气3房，首付19万，南北通透，铂金3楼，临地铁",
    "xiaoqu_": "五院家属院",
    "room": "3室2厅",
    "total_price": "112",
    "url": "http://m.fang.com/esf/zz/JHAGT_180854659_17655779x2510466269_163498804.html",
    "price": "10959元/㎡ ",
    "louceng": "低层/7层",
    "louxing": "南北",
    "chaoxiang": "精装修",
    "zhuangxiu": "有",
    "age": "1999",
    "quyu": "金水-水上乐园",
    "shoufu": "",
    "xiaoqu": "五院家属院",
    "position": 3
  },
  {
    "id": "2510466269",
    "area": "70",
    "feature": "满五",
    "title": "文化路黄河路，五院家属院，双气两房，三楼，南北通透，停车便",
    "xiaoqu_": "五院家属院",
    "room": "2室1厅",
    "total_price": "75",
    "url": "http://m.fang.com/esf/zz/JHAGT_180789624_16746586x2510466269_163973456.html",
    "price": "10714元/㎡ ",
    "louceng": "中层/7层",
    "louxing": "板楼",
    "chaoxiang": "南北",
    "zhuangxiu": "中装修",
    "age": "有",
    "quyu": "1998",
    "": "金水-水上乐园",
    "shoufu": "",
    "xiaoqu": "五院家属院",
    "position": 4
  },
  {
    "id": "2510466269",
    "area": "131",
    "feature": "满五",
    "title": "黄河路文化路（10年电梯三房）婚房精装修（均价一万二）送家电",
    "xiaoqu_": "五院家属院",
    "room": "3室2厅",
    "total_price": "160",
    "url": "http://m.fang.com/esf/zz/JHAGT_180880696_17676266x2510466269_163651854.html",
    "price": "12214元/㎡ ",
    "louceng": "中层/12层",
    "louxing": "板楼",
    "chaoxiang": "南北",
    "zhuangxiu": "精装修",
    "age": "有",
    "quyu": "2010",
    "": "金水-水上乐园",
    "shoufu": "",
    "xiaoqu": "五院家属院",
    "position": 5
  },
  {
    "id": "2510466269",
    "area": "76",
    "feature": "满五",
    "title": "劲爆！文化路红旗路五院家属院低总价双气两房好楼层停车方便",
    "xiaoqu_": "五院家属院",
    "room": "2室2厅",
    "total_price": "84",
    "url": "http://m.fang.com/esf/zz/JHAGT_180885253_16764991x2510466269_166145727.html",
    "price": "11053元/㎡ ",
    "louceng": "中层/7层",
    "louxing": "板楼",
    "chaoxiang": "南",
    "zhuangxiu": "中装修",
    "age": "有",
    "quyu": "有",
    "": "金水-水上乐园",
    "shoufu": "",
    "xiaoqu": "五院家属院",
    "position": 6
  },
  {
    "id": "2510466269",
    "area": "75",
    "feature": "满五",
    "title": "新出！地铁口 市五院家属院 双气精装修 通透采光好 看房随时",
    "xiaoqu_": "五院家属院",
    "room": "2室1厅",
    "total_price": "78",
    "url": "http://m.fang.com/esf/zz/JHAGT_180869342_17668603x2510466269_164331581.html",
    "price": "10400元/㎡ ",
    "louceng": "高层/8层",
    "louxing": "塔板结合",
    "chaoxiang": "南北",
    "zhuangxiu": "精装修",
    "age": "有",
    "quyu": "有",
    "": "金水-水上乐园",
    "shoufu": "",
    "xiaoqu": "五院家属院",
    "position": 7
  },
  {
    "id": "2510466269",
    "area": "69",
    "feature": "满五",
    "title": "文化路黄河路,五院家属院,首付18万,双气全明两室,划-片文",
    "xiaoqu_": "五院家属院",
    "room": "2室1厅",
    "total_price": "80",
    "url": "http://m.fang.com/esf/zz/JHAGT_180887909_17101337x2510466269_166376662.html",
    "price": "11594元/㎡ ",
    "louceng": "低层/8层",
    "louxing": "板楼",
    "chaoxiang": "南北",
    "zhuangxiu": "精装修",
    "age": "有",
    "quyu": "有",
    "": "金水-水上乐园",
    "shoufu": "",
    "xiaoqu": "五院家属院",
    "position": 8
  },
  {
    "id": "2510466269",
    "area": "88.7",
    "feature": "配套成熟",
    "title": "劲爆市五院2楼，大两室，户型正首付25万，南北通透，急售",
    "xiaoqu_": "五院家属院",
    "room": "2室2厅",
    "total_price": "99",
    "url": "http://m.fang.com/esf/zz/JHAGT_180786746_17581634x2510466269_163378952.html",
    "price": "11161元/㎡ ",
    "louceng": "低层/7层",
    "louxing": "板楼",
    "chaoxiang": "南北",
    "zhuangxiu": "精装修",
    "age": "2001",
    "quyu": "金水-水上乐园",
    "shoufu": "",
    "xiaoqu": "五院家属院",
    "position": 9
  },
  {
    "id": "2510466269",
    "area": "87",
    "feature": "满五",
    "title": "文化路黄河路口，双气大两室，3楼南北通透，谁看谁相中",
    "xiaoqu_": "五院家属院",
    "room": "2室2厅",
    "total_price": "105",
    "url": "http://m.fang.com/esf/zz/JHAGT_180885724_17526507x2510466269_166799959.html",
    "price": "12069元/㎡ ",
    "louceng": "中层/7层",
    "louxing": "南北",
    "chaoxiang": "精装修",
    "zhuangxiu": "有",
    "age": "2002",
    "quyu": "金水-水上乐园",
    "shoufu": "",
    "xiaoqu": "五院家属院",
    "position": 10
  },
  {
    "id": "2510466269",
    "area": "94.63",
    "feature": "满五",
    "title": "五院家属院 多层3楼 双气3房 上 文化路2小 停车方便 急售",
    "xiaoqu_": "五院家属院",
    "room": "3室2厅",
    "total_price": "117",
    "url": "http://m.fang.com/esf/zz/JHAGT_180795593_17545248x2510466269_163973456.html",
    "price": "12364元/㎡ ",
    "louceng": "中层/7层",
    "louxing": "板楼",
    "chaoxiang": "南北",
    "zhuangxiu": "精装修",
    "age": "2000",
    "quyu": "金水-水上乐园",
    "shoufu": "",
    "xiaoqu": "五院家属院",
    "position": 11
  },
  {
    "id": "2510466269",
    "area": "113.65",
    "feature": "满五",
    "title": "五院家属院 均价一万一 多层2楼 精装3房 停车方便 上 文化2小。",
    "xiaoqu_": "五院家属院",
    "room": "3室2厅",
    "total_price": "130",
    "url": "http://m.fang.com/esf/zz/JHAGT_180815106_17622721x2510466269_166562427.html",
    "price": "11439元/㎡ ",
    "louceng": "低层/7层",
    "louxing": "板楼",
    "chaoxiang": "南北",
    "zhuangxiu": "精装修",
    "age": "2000",
    "quyu": "金水-水上乐园",
    "shoufu": "",
    "xiaoqu": "五院家属院",
    "position": 12
  },
  {
    "id": "2510466269",
    "area": "75",
    "feature": "满五",
    "title": "首付20万住文化路黄河路旁，双气低楼层全明两室，均价1万上文",
    "xiaoqu_": "五院家属院",
    "room": "2室1厅",
    "total_price": "78",
    "url": "http://m.fang.com/esf/zz/JHAGT_180852905_16902182x2510466269_163566161.html",
    "price": "10400元/㎡ ",
    "louceng": "中层/7层",
    "louxing": "板楼",
    "chaoxiang": "南北",
    "zhuangxiu": "精装修",
    "age": "有",
    "quyu": "有",
    "": "金水-水上乐园",
    "shoufu": "",
    "xiaoqu": "五院家属院",
    "position": 13
  },
  {
    "id": "2510466269",
    "area": "90",
    "feature": "满五",
    "title": "保真 5号线人民医院地铁口 精装双气 低于市场价",
    "xiaoqu_": "五院家属院",
    "room": "2室2厅",
    "total_price": "100",
    "url": "http://m.fang.com/esf/zz/JHAGT_180156849_17644629x2510466269_166649012.html",
    "price": "11111元/㎡ ",
    "louceng": "中层/7层",
    "louxing": "钢混",
    "chaoxiang": "南",
    "zhuangxiu": "精装修",
    "age": "1997",
    "quyu": "金水-水上乐园",
    "shoufu": "",
    "xiaoqu": "五院家属院",
    "position": 14
  },
  {
    "id": "2510466269",
    "area": "68.8",
    "feature": "满五,采光好",
    "title": "文化，市五院旁，精装双气2房，南北通透，停车方便",
    "xiaoqu_": "五院家属院",
    "room": "2室1厅",
    "total_price": "65",
    "url": "http://m.fang.com/esf/zz/JHAGT_180867732_16924307x2510466269_162240837.html",
    "price": "9448元/㎡ ",
    "louceng": "中层/7层",
    "louxing": "板楼",
    "chaoxiang": "南北",
    "zhuangxiu": "精装修",
    "age": "有",
    "quyu": "1998",
    "": "金水-水上乐园",
    "shoufu": "",
    "xiaoqu": "五院家属院",
    "position": 15
  }
]