[
  {
    "dt": [
      {
        "tit": "齐礼阎",
        "jl": "1305米",
        "desc": "5号线"
      },
      {
        "tit": "市第二人民医院",
        "jl": "1660米",
        "desc": "5号线"
      },
      {
        "tit": "后河芦",
        "jl": "1669米",
        "desc": "5号线"
      },
      {
        "tit": "桐淮",
        "jl": "1692米",
        "desc": "5号线"
      },
      {
        "tit": "陇海西路",
        "jl": "1720米",
        "desc": "5号线"
      },
      {
        "tit": "绿城广场",
        "jl": "1782米",
        "desc": "1号线"
      },
      {
        "tit": "医学院",
        "jl": "2024米",
        "desc": "1号线"
      },
      {
        "tit": "市中心医院",
        "jl": "2347米",
        "desc": "5号线"
      }
    ],
    "gj": [
      {
        "tit": "汝河路兴华街",
        "jl": "117米",
        "desc": "204路,210路,291路,s139路,"
      },
      {
        "tit": "兴华街汝河路",
        "jl": "132米",
        "desc": "46路,49路,138路,903路,y15路,"
      },
      {
        "tit": "绿云小区",
        "jl": "230米",
        "desc": "46路,49路,138路,903路,s139路,y15路,"
      },
      {
        "tit": "淮河路兴华街站",
        "jl": "343米",
        "desc": "20路,126路,203路,210路,y2路,"
      },
      {
        "tit": "淮河路嵩山路",
        "jl": "391米",
        "desc": "20路,126路,138路,203路,y2路,"
      },
      {
        "tit": "淮北街汝河路",
        "jl": "404米",
        "desc": "256路,291路,s125路,"
      },
      {
        "tit": "嵩山路淮河路",
        "jl": "430米",
        "desc": "63路,63路,区间82路,84路,560路,b11路,"
      },
      {
        "tit": "汝河路嵩山路",
        "jl": "450米",
        "desc": "58路,204路,210路,291路,s139路,"
      },
      {
        "tit": "淮南街淮河路",
        "jl": "461米",
        "desc": "256路,291路,s125路,"
      },
      {
        "tit": "淮河路淮北街",
        "jl": "569米",
        "desc": "20路,46路,126路,203路,210路,y2路,"
      }
    ],
    "xx": [
      {
        "tit": "新概念外语学校",
        "jl": "184米",
        "desc": ""
      },
      {
        "tit": "郑州锐林辅导学校",
        "jl": "242米",
        "desc": ""
      },
      {
        "tit": "郑州市第二十二中学",
        "jl": "757米",
        "desc": ""
      },
      {
        "tit": "车老师中高考辅导学校(嵩山路校区)",
        "jl": "401米",
        "desc": ""
      },
      {
        "tit": "郑州市五十七中学区兴华中学",
        "jl": "740米",
        "desc": ""
      },
      {
        "tit": "郑州爱中学校",
        "jl": "772米",
        "desc": ""
      },
      {
        "tit": "河南电力职工大学",
        "jl": "279米",
        "desc": ""
      },
      {
        "tit": "郑州第二中学",
        "jl": "1075米",
        "desc": ""
      },
      {
        "tit": "河南工业大学(嵩山南路校区)",
        "jl": "1124米",
        "desc": ""
      },
      {
        "tit": "郑州大学(南校区)",
        "jl": "1383米",
        "desc": ""
      }
    ],
    "yy": [
      {
        "tit": "郑州市骨科医院",
        "jl": "810米",
        "desc": ""
      },
      {
        "tit": "郑州市第二人民医院",
        "jl": "1320米",
        "desc": ""
      },
      {
        "tit": "郑州市中心医院妇女健康管理中心",
        "jl": "1413米",
        "desc": ""
      },
      {
        "tit": "河南电力医院",
        "jl": "583米",
        "desc": ""
      },
      {
        "tit": "郑州康好医院",
        "jl": "1171米",
        "desc": ""
      },
      {
        "tit": "郑州二七区女子医院",
        "jl": "286米",
        "desc": ""
      },
      {
        "tit": "郑州协和医院",
        "jl": "1963米",
        "desc": ""
      },
      {
        "tit": "河南工业大学校医院",
        "jl": "942米",
        "desc": ""
      },
      {
        "tit": "郑州康宸医院",
        "jl": "1175米",
        "desc": ""
      },
      {
        "tit": "郑州交通医院",
        "jl": "1534米",
        "desc": ""
      }
    ],
    "gw": [
      {
        "tit": "郑州市平价蔬菜超市",
        "jl": "223米",
        "desc": ""
      },
      {
        "tit": "泰得城",
        "jl": "542米",
        "desc": ""
      },
      {
        "tit": "恒达百货超市",
        "jl": "99米",
        "desc": ""
      },
      {
        "tit": "红发超市",
        "jl": "98米",
        "desc": ""
      },
      {
        "tit": "锦绣坊服装工作室",
        "jl": "43米",
        "desc": ""
      },
      {
        "tit": "雅堂小超(民安路店)",
        "jl": "134米",
        "desc": ""
      },
      {
        "tit": "九九超市",
        "jl": "149米",
        "desc": ""
      },
      {
        "tit": "丹尼斯超市(安康店)",
        "jl": "733米",
        "desc": ""
      },
      {
        "tit": "路砦生活广场",
        "jl": "545米",
        "desc": ""
      },
      {
        "tit": "柯圃连锁超市(淮北街店)",
        "jl": "390米",
        "desc": ""
      }
    ],
    "yh": [
      {
        "tit": "郑州农商银行(兴华南路分社)",
        "jl": "160米",
        "desc": ""
      },
      {
        "tit": "中国光大银行24小时自助银行(郑州淮河路支行)",
        "jl": "258米",
        "desc": ""
      },
      {
        "tit": "中国光大银行(郑州淮河路支行)",
        "jl": "289米",
        "desc": ""
      },
      {
        "tit": "中国工商银行(郑州兴华南街支行)",
        "jl": "295米",
        "desc": ""
      },
      {
        "tit": "郑州银行24小时自助银行(西建材支行)",
        "jl": "315米",
        "desc": ""
      },
      {
        "tit": "中国工商银行24小时自助银行服务(郑州兴华南街支行)",
        "jl": "318米",
        "desc": ""
      },
      {
        "tit": "郑州银行(西建材支行)",
        "jl": "325米",
        "desc": ""
      },
      {
        "tit": "中原银行24小时自助银行(汝河路店)",
        "jl": "466米",
        "desc": ""
      },
      {
        "tit": "中国邮政储蓄银行24小时自助银行(陇西营业所)",
        "jl": "535米",
        "desc": ""
      },
      {
        "tit": "中国建设银行24小时自助银行(郑州齐礼闫支行)",
        "jl": "587米",
        "desc": ""
      }
    ],
    "position": 1
  }
]