[
  {
    "dt": [
      {
        "tit": "二七广场",
        "jl": "660米",
        "desc": "1号线"
      },
      {
        "tit": "郑州火车站",
        "jl": "1163米",
        "desc": "1号线"
      },
      {
        "tit": "东大街",
        "jl": "1235米",
        "desc": "2号线"
      },
      {
        "tit": "人民路",
        "jl": "1236米",
        "desc": "1号线"
      },
      {
        "tit": "陇海东路",
        "jl": "1587米",
        "desc": "2号线"
      },
      {
        "tit": "紫荆山",
        "jl": "2070米",
        "desc": "1号线2号线"
      },
      {
        "tit": "二里岗",
        "jl": "2345米",
        "desc": "2号线"
      }
    ],
    "gj": [
      {
        "tit": "大同路德化街",
        "jl": "156米",
        "desc": "98路,"
      },
      {
        "tit": "市第三人民医院",
        "jl": "163米",
        "desc": "38路,98路,136路,206路,556路,游51支"
      },
      {
        "tit": "南顺城街大同路",
        "jl": "207米",
        "desc": "98路,"
      },
      {
        "tit": "福寿街大同路站",
        "jl": "311米",
        "desc": "2路,6路,区间21路,29路,32路,38路,98路,729路,985路,b17路,y15路,"
      },
      {
        "tit": "火车站南港湾",
        "jl": "461米",
        "desc": "2路,206路,315支线325专线553路,985路,b17路,y15路,y3路,y9路,"
      },
      {
        "tit": "锦荣商贸城",
        "jl": "549米",
        "desc": "1路,13路,20路,29路,136路,206路,729路,y3路,y9路,"
      },
      {
        "tit": "二七广场正兴街",
        "jl": "722米",
        "desc": "2路,6路,6路,区间9路,26路,28路,32路,34路,35路,40路,52路,60路,85路,109路,603路,900路,903路,906路,966路,y10路,y11路,y12路,y1路,y5路,y6路,游51路,"
      },
      {
        "tit": "西大街南下街",
        "jl": "517米",
        "desc": "35路,60路,78路,85路,985路,y12路,y5路,游51路,"
      },
      {
        "tit": "银基",
        "jl": "312米",
        "desc": "556路,"
      },
      {
        "tit": "西大街顺城街",
        "jl": "571米",
        "desc": "35路,60路,78路,85路,y12路,y5路,"
      }
    ],
    "xx": [
      {
        "tit": "郑州市扶轮外国语学校",
        "jl": "391米",
        "desc": ""
      },
      {
        "tit": "郑州市第三中学",
        "jl": "589米",
        "desc": ""
      },
      {
        "tit": "郑州市汇美晟典职业培训学校",
        "jl": "345米",
        "desc": ""
      },
      {
        "tit": "郑州市豫翔实验学校",
        "jl": "506米",
        "desc": ""
      },
      {
        "tit": "郑州市扶轮外国语学校-招生咨询处",
        "jl": "417米",
        "desc": ""
      },
      {
        "tit": "南关小学",
        "jl": "774米",
        "desc": ""
      },
      {
        "tit": "郑州师院信息技术学校校区",
        "jl": "907米",
        "desc": ""
      },
      {
        "tit": "郑州市第四十五中学",
        "jl": "914米",
        "desc": ""
      },
      {
        "tit": "管城回族区辅读学校",
        "jl": "516米",
        "desc": ""
      },
      {
        "tit": "郑州市盲聋哑学校",
        "jl": "965米",
        "desc": ""
      }
    ],
    "yy": [
      {
        "tit": "郑州市二七区人民医院",
        "jl": "439米",
        "desc": ""
      },
      {
        "tit": "河南中医药大学第一附属医院",
        "jl": "1410米",
        "desc": ""
      },
      {
        "tit": "郑州第一人民医院",
        "jl": "1500米",
        "desc": ""
      },
      {
        "tit": "郑州市第三人民医院-2号楼",
        "jl": "179米",
        "desc": ""
      },
      {
        "tit": "郑州市第二中医院",
        "jl": "891米",
        "desc": ""
      },
      {
        "tit": "金氏祖传",
        "jl": "100米",
        "desc": ""
      },
      {
        "tit": "郑州市第三人民医院-导管室",
        "jl": "204米",
        "desc": ""
      },
      {
        "tit": "郑州大学第五附属医院",
        "jl": "1592米",
        "desc": ""
      },
      {
        "tit": "郑州市第三人民医院-7号楼",
        "jl": "288米",
        "desc": ""
      },
      {
        "tit": "武警河南总队医院",
        "jl": "1792米",
        "desc": ""
      }
    ],
    "gw": [
      {
        "tit": "无限城购物中心",
        "jl": "309米",
        "desc": ""
      },
      {
        "tit": "美意生活超市",
        "jl": "70米",
        "desc": ""
      },
      {
        "tit": "大同百货超市",
        "jl": "248米",
        "desc": ""
      },
      {
        "tit": "百世邻里昊昊超市",
        "jl": "158米",
        "desc": ""
      },
      {
        "tit": "便民超市",
        "jl": "155米",
        "desc": ""
      },
      {
        "tit": "悦东粮油商行",
        "jl": "8米",
        "desc": ""
      },
      {
        "tit": "家乡超市(弓背街店)",
        "jl": "117米",
        "desc": ""
      },
      {
        "tit": "永发超市",
        "jl": "143米",
        "desc": ""
      },
      {
        "tit": "世纪华联超市(大同路店)",
        "jl": "303米",
        "desc": ""
      },
      {
        "tit": "郑州箱包皮具城",
        "jl": "150米",
        "desc": ""
      }
    ],
    "yh": [
      {
        "tit": "农村商业银行(德化街分社)",
        "jl": "161米",
        "desc": ""
      },
      {
        "tit": "中国工商银行24小时自助银行服务(郑州大同路支行)",
        "jl": "382米",
        "desc": ""
      },
      {
        "tit": "广发银行(银基支行)",
        "jl": "426米",
        "desc": ""
      },
      {
        "tit": "上海浦东发展银行(郑州银基商贸城小微支行)",
        "jl": "446米",
        "desc": ""
      },
      {
        "tit": "上海浦东发展银行24小时自助银行(郑州银基商贸城小微支行)",
        "jl": "464米",
        "desc": ""
      },
      {
        "tit": "上海浦东发展银行24小时自助银行(东三马路18号院西南)",
        "jl": "480米",
        "desc": ""
      },
      {
        "tit": "交通银行(郑州西大街支行)",
        "jl": "482米",
        "desc": ""
      },
      {
        "tit": "郑州银行(西大街支行)",
        "jl": "492米",
        "desc": ""
      },
      {
        "tit": "交通银行24小时自助银行(郑州西大街支行)",
        "jl": "494米",
        "desc": ""
      },
      {
        "tit": "郑州银行24小时自助银行(西大街支行)",
        "jl": "499米",
        "desc": ""
      }
    ],
    "position": 1
  }
]