[
  {
    "dt": [
      {
        "tit": "市第二人民医院",
        "jl": "1888米",
        "desc": "5号线"
      },
      {
        "tit": "京广南路",
        "jl": "2130米",
        "desc": "5号线"
      },
      {
        "tit": "齐礼阎",
        "jl": "2423米",
        "desc": "5号线"
      }
    ],
    "gj": [
      {
        "tit": "赣江路大学路",
        "jl": "29米",
        "desc": "b16路,"
      },
      {
        "tit": "建云街赣江路",
        "jl": "101米",
        "desc": "291路,"
      },
      {
        "tit": "赣江路王胡寨",
        "jl": "158米",
        "desc": "318路,563路,b16路,"
      },
      {
        "tit": "大学路王胡寨站",
        "jl": "169米",
        "desc": "40路,84路,176路,180路,204路,904路,b10路,b16路,b60路,s139路,y21路,"
      },
      {
        "tit": "建云街郑航街",
        "jl": "213米",
        "desc": "291路,"
      },
      {
        "tit": "郑航街建云街",
        "jl": "274米",
        "desc": "291路,"
      },
      {
        "tit": "郑航街大学路",
        "jl": "296米",
        "desc": "291路,s139路,"
      },
      {
        "tit": "沅江路行云路",
        "jl": "364米",
        "desc": "291路,"
      },
      {
        "tit": "行云路赣江路",
        "jl": "426米",
        "desc": "298路,b16路,"
      },
      {
        "tit": "大学路长江路站",
        "jl": "555米",
        "desc": "40路,84路,176路,180路,204路,552路,904路,b10路,b16路,b60路,y21路,"
      }
    ],
    "xx": [
      {
        "tit": "郑州创牌高级制版培训",
        "jl": "236米",
        "desc": ""
      },
      {
        "tit": "郑州市第四十八中学",
        "jl": "601米",
        "desc": ""
      },
      {
        "tit": "高燕外语培训学校(王胡寨校区)",
        "jl": "329米",
        "desc": ""
      },
      {
        "tit": "郑州市第八十一中学",
        "jl": "664米",
        "desc": ""
      },
      {
        "tit": "郑州市第九十二中学",
        "jl": "660米",
        "desc": ""
      },
      {
        "tit": "郑州市二七区辅读学校",
        "jl": "509米",
        "desc": ""
      },
      {
        "tit": "郑州市第七十四中学",
        "jl": "900米",
        "desc": ""
      },
      {
        "tit": "郑州中原理工专修学院",
        "jl": "948米",
        "desc": ""
      },
      {
        "tit": "郑州航空工业管理学院(大学路校区)",
        "jl": "1472米",
        "desc": ""
      },
      {
        "tit": "剑桥外语学校",
        "jl": "705米",
        "desc": ""
      }
    ],
    "yy": [
      {
        "tit": "郑州市第六人民医院",
        "jl": "1484米",
        "desc": ""
      },
      {
        "tit": "二七区第二人民医院",
        "jl": "211米",
        "desc": ""
      },
      {
        "tit": "郑州市第六人民医院-门诊楼",
        "jl": "1460米",
        "desc": ""
      },
      {
        "tit": "郑州市第六人民医院-8号楼",
        "jl": "1493米",
        "desc": ""
      },
      {
        "tit": "郑州金成中医风湿病医院",
        "jl": "665米",
        "desc": ""
      },
      {
        "tit": "郑州市精神病防治医院",
        "jl": "1739米",
        "desc": ""
      },
      {
        "tit": "郑州爱尔眼科医院",
        "jl": "1931米",
        "desc": ""
      },
      {
        "tit": "郑州市社区卫生服务中心(郑飞国际酒店北)",
        "jl": "873米",
        "desc": ""
      },
      {
        "tit": "京广路社区卫生服务中心",
        "jl": "1460米",
        "desc": ""
      },
      {
        "tit": "郑州市尧典御医馆",
        "jl": "1082米",
        "desc": ""
      }
    ],
    "gw": [
      {
        "tit": "好乐多超市",
        "jl": "19米",
        "desc": ""
      },
      {
        "tit": "满意100超市(赣江路店)",
        "jl": "40米",
        "desc": ""
      },
      {
        "tit": "好贝贝超市",
        "jl": "49米",
        "desc": ""
      },
      {
        "tit": "正道思达超市(大学路店)",
        "jl": "213米",
        "desc": ""
      },
      {
        "tit": "世纪华联生活超市(大学路店)",
        "jl": "312米",
        "desc": ""
      },
      {
        "tit": "华联生活超市(仁和路店)",
        "jl": "500米",
        "desc": ""
      },
      {
        "tit": "丹尼斯全日鲜(中秋路店)",
        "jl": "314米",
        "desc": ""
      },
      {
        "tit": "大明眼镜(南湾路店)",
        "jl": "104米",
        "desc": ""
      },
      {
        "tit": "百果园(海悦雅居店)",
        "jl": "84米",
        "desc": ""
      },
      {
        "tit": "华府超市(中秋路店)",
        "jl": "330米",
        "desc": ""
      }
    ],
    "yh": [
      {
        "tit": "建设银行24小时自助银行服务(郑州大学南路支行)",
        "jl": "82米",
        "desc": ""
      },
      {
        "tit": "中国建设银行(郑州大学南路支行)",
        "jl": "93米",
        "desc": ""
      },
      {
        "tit": "中国农业银行(郑州大学南路支行)",
        "jl": "152米",
        "desc": ""
      },
      {
        "tit": "中国农业银行24小时自助银行服务(郑州大学南路支行)",
        "jl": "152米",
        "desc": ""
      },
      {
        "tit": "郑州银行(大学路支行)",
        "jl": "153米",
        "desc": ""
      },
      {
        "tit": "郑州银行24小时自助银行服务(大学路支行)",
        "jl": "158米",
        "desc": ""
      },
      {
        "tit": "郑州农商银行(王胡砦支行)24小时ATM",
        "jl": "159米",
        "desc": ""
      },
      {
        "tit": "郑州市市区农村信用合作联社24小时自助银行(二七分社)",
        "jl": "221米",
        "desc": ""
      },
      {
        "tit": "中国邮政储蓄银行",
        "jl": "340米",
        "desc": ""
      },
      {
        "tit": "中国邮政储蓄银行(1084邮局营业部)",
        "jl": "568米",
        "desc": ""
      }
    ],
    "position": 1
  }
]