[
  {
    "dt": [
      {
        "tit": "碧沙岗",
        "jl": "848米",
        "desc": "1号线"
      },
      {
        "tit": "月季公园",
        "jl": "858米",
        "desc": "5号线"
      },
      {
        "tit": "沙口路",
        "jl": "1463米",
        "desc": "5号线"
      },
      {
        "tit": "绿城广场",
        "jl": "1510米",
        "desc": "1号线"
      },
      {
        "tit": "五一公园",
        "jl": "1649米",
        "desc": "1号线5号线"
      },
      {
        "tit": "医学院",
        "jl": "1846米",
        "desc": "1号线"
      },
      {
        "tit": "市中心医院",
        "jl": "2186米",
        "desc": "5号线"
      },
      {
        "tit": "海滩寺",
        "jl": "2330米",
        "desc": "5号线"
      }
    ],
    "gj": [
      {
        "tit": "嵩山路棉纺路",
        "jl": "288米",
        "desc": "50路,83路,130路,289路,b11路,y20路,"
      },
      {
        "tit": "金水路嵩山北路",
        "jl": "382米",
        "desc": "k901路,"
      },
      {
        "tit": "金水西路嵩山北路",
        "jl": "400米",
        "desc": "130路,289路,"
      },
      {
        "tit": "棉纺路嵩山路",
        "jl": "450米",
        "desc": "34路,37路,45路,49路,76路,79路,211路,s170路,y20路,y22路,"
      },
      {
        "tit": "嵩山路西站路",
        "jl": "456米",
        "desc": "50路,83路,130路,b11路,y20路,"
      },
      {
        "tit": "嵩山路建设路",
        "jl": "601米",
        "desc": "49路,83路,211路,"
      },
      {
        "tit": "纺织大世界",
        "jl": "689米",
        "desc": "289路,"
      },
      {
        "tit": "棉纺东路",
        "jl": "776米",
        "desc": "34路,37路,45路,49路,76路,211路,s170路,y22路,"
      },
      {
        "tit": "棉纺西路",
        "jl": "853米",
        "desc": "34路,37路,45路,76路,y22路,"
      },
      {
        "tit": "西站路嵩山路",
        "jl": "380米",
        "desc": "289路,"
      }
    ],
    "xx": [
      {
        "tit": "郑州市第六十八中学",
        "jl": "289米",
        "desc": ""
      },
      {
        "tit": "联大外国语学校(锦江校区)",
        "jl": "452米",
        "desc": ""
      },
      {
        "tit": "标榜美容美发学校",
        "jl": "477米",
        "desc": ""
      },
      {
        "tit": "流碧高考学校",
        "jl": "570米",
        "desc": ""
      },
      {
        "tit": "欧雅商务标榜学校",
        "jl": "525米",
        "desc": ""
      },
      {
        "tit": "屯蒙教育综合培训学校",
        "jl": "543米",
        "desc": ""
      },
      {
        "tit": "郑州东方艺术中等专业学校",
        "jl": "662米",
        "desc": ""
      },
      {
        "tit": "郑州市第五十二中学",
        "jl": "1322米",
        "desc": ""
      },
      {
        "tit": "育红小学",
        "jl": "1029米",
        "desc": ""
      },
      {
        "tit": "当代教育日韩语培训学校",
        "jl": "863米",
        "desc": ""
      }
    ],
    "yy": [
      {
        "tit": "郑州市中医院",
        "jl": "1564米",
        "desc": ""
      },
      {
        "tit": "郑州大学第一附属医院(河医院区)",
        "jl": "1683米",
        "desc": ""
      },
      {
        "tit": "河南省医药科学研究院附属医院",
        "jl": "1946米",
        "desc": ""
      },
      {
        "tit": "水工医院",
        "jl": "570米",
        "desc": ""
      },
      {
        "tit": "郑州豫欣医院",
        "jl": "586米",
        "desc": ""
      },
      {
        "tit": "郑州市社区卫生服务中心(五里堡办事处)",
        "jl": "561米",
        "desc": ""
      },
      {
        "tit": "中国人民解放军第九八八医院(空军医院院区)",
        "jl": "1289米",
        "desc": ""
      },
      {
        "tit": "郑州市二七区红十字医院",
        "jl": "817米",
        "desc": ""
      },
      {
        "tit": "郑州中泰脑科医院",
        "jl": "795米",
        "desc": ""
      },
      {
        "tit": "河南省口腔医院",
        "jl": "1940米",
        "desc": ""
      }
    ],
    "gw": [
      {
        "tit": "丹尼斯(中原店)",
        "jl": "372米",
        "desc": ""
      },
      {
        "tit": "中原商贸城",
        "jl": "929米",
        "desc": ""
      },
      {
        "tit": "雯雯超市",
        "jl": "58米",
        "desc": ""
      },
      {
        "tit": "丹尼斯全日鲜(建设店)",
        "jl": "726米",
        "desc": ""
      },
      {
        "tit": "地利生鲜(嵩山北路店)",
        "jl": "454米",
        "desc": ""
      },
      {
        "tit": "家辉生鲜(建设路店)",
        "jl": "759米",
        "desc": ""
      },
      {
        "tit": "宏江中央广场",
        "jl": "388米",
        "desc": ""
      },
      {
        "tit": "云和花鲜花店",
        "jl": "77米",
        "desc": ""
      },
      {
        "tit": "众品冷鲜肉超市",
        "jl": "63米",
        "desc": ""
      },
      {
        "tit": "胖子便民平价水果蔬菜",
        "jl": "153米",
        "desc": ""
      }
    ],
    "yh": [
      {
        "tit": "中国工商银行24小时自助银行服务(郑州棉纺东路支行)",
        "jl": "405米",
        "desc": ""
      },
      {
        "tit": "中国工商银行24小时自助银行(郑州棉纺东路支行)",
        "jl": "671米",
        "desc": ""
      },
      {
        "tit": "中国工商银行(郑州棉纺东路支行)",
        "jl": "674米",
        "desc": ""
      },
      {
        "tit": "中国银行(郑州棉纺东路支行)",
        "jl": "699米",
        "desc": ""
      },
      {
        "tit": "华夏银行24小时自助银行(郑州建设路支行)",
        "jl": "795米",
        "desc": ""
      },
      {
        "tit": "华夏银行(郑州建设路支行)",
        "jl": "803米",
        "desc": ""
      },
      {
        "tit": "郑州市市区农村信用合作联社",
        "jl": "811米",
        "desc": ""
      },
      {
        "tit": "郑州农商银行24小时自助银行服务(嵩山北路店)",
        "jl": "812米",
        "desc": ""
      },
      {
        "tit": "郑州市金水区农村信用合作社(北二环分社)",
        "jl": "835米",
        "desc": ""
      },
      {
        "tit": "中国工商银行(郑州建设路支行)",
        "jl": "870米",
        "desc": ""
      }
    ],
    "position": 1
  }
]