[
  {
    "dt": [
      {
        "tit": "中央商务区",
        "jl": "775米",
        "desc": "5号线"
      },
      {
        "tit": "儿童医院",
        "jl": "973米",
        "desc": "5号线"
      },
      {
        "tit": "黄河南路",
        "jl": "1794米",
        "desc": "1号线"
      },
      {
        "tit": "会展中心",
        "jl": "1869米",
        "desc": "1号线"
      },
      {
        "tit": "众意西路",
        "jl": "1957米",
        "desc": "5号线"
      },
      {
        "tit": "农业南路",
        "jl": "2006米",
        "desc": "1号线"
      }
    ],
    "gj": [
      {
        "tit": "九如路天韵街",
        "jl": "147米",
        "desc": "195路,s138路,"
      },
      {
        "tit": "九如路龙湖外环南路",
        "jl": "171米",
        "desc": "s138路,"
      },
      {
        "tit": "龙湖外环南路九如东路",
        "jl": "361米",
        "desc": "s175路,"
      },
      {
        "tit": "黄河东路九如路",
        "jl": "443米",
        "desc": "47路,75路,186路,188路,312路,s138路,"
      },
      {
        "tit": "九如路农业东路",
        "jl": "447米",
        "desc": "65路,97路,195路,s131路,s138路,"
      },
      {
        "tit": "农业东路九如路",
        "jl": "448米",
        "desc": "48路,65路,97路,158路,166路,195路,b2路,支线k905路,s128路,s129路,s131路,y1路,"
      },
      {
        "tit": "农业东路九如东路",
        "jl": "533米",
        "desc": "48路,97路,158路,166路,195路,b2路,支线s128路,y1路,"
      },
      {
        "tit": "民航花园公交站",
        "jl": "747米",
        "desc": "48路,65路,97路,158路,166路,193路,b2路,支线s128路,y1路,"
      },
      {
        "tit": "黄河东路九如东路",
        "jl": "545米",
        "desc": "47路,162路,186路,188路,312路,s138路,"
      },
      {
        "tit": "商务外环路九如东路",
        "jl": "706米",
        "desc": "23路,26路,206路,b53路,y23路,智慧岛便民服务车智慧岛便民直通车"
      }
    ],
    "xx": [
      {
        "tit": "新东方(郑东中学中小学全科辅导中心)",
        "jl": "202米",
        "desc": ""
      },
      {
        "tit": "郑州市郑东新区外国语中学",
        "jl": "238米",
        "desc": ""
      },
      {
        "tit": "奇语妙言语言艺术学校(宝龙城市广场B区店)",
        "jl": "350米",
        "desc": ""
      },
      {
        "tit": "郑州市郑东新区外国语学校",
        "jl": "555米",
        "desc": ""
      },
      {
        "tit": "大山中学生·一对一教学中心(宝龙城市广场)",
        "jl": "442米",
        "desc": ""
      },
      {
        "tit": "河南省实验学校郑东小学",
        "jl": "506米",
        "desc": ""
      },
      {
        "tit": "郑州市第四十七中学",
        "jl": "818米",
        "desc": ""
      },
      {
        "tit": "河南省实验学校郑东小学-当代教育",
        "jl": "376米",
        "desc": ""
      },
      {
        "tit": "如意湖家庭教育学校",
        "jl": "581米",
        "desc": ""
      },
      {
        "tit": "教育部中国书画等级考试ccpt河南省实验学校郑东小学考试点",
        "jl": "462米",
        "desc": ""
      }
    ],
    "yy": [
      {
        "tit": "郑州颐和医院",
        "jl": "749米",
        "desc": ""
      },
      {
        "tit": "河南省直第三人民医院",
        "jl": "1549米",
        "desc": ""
      },
      {
        "tit": "河南省儿童医院东区-医技楼F区",
        "jl": "1180米",
        "desc": ""
      },
      {
        "tit": "郑州颐和医院-住院部B",
        "jl": "804米",
        "desc": ""
      },
      {
        "tit": "美美医疗美容",
        "jl": "574米",
        "desc": ""
      },
      {
        "tit": "郑州颐和医院-住院部D",
        "jl": "723米",
        "desc": ""
      },
      {
        "tit": "河南省儿童医院东区",
        "jl": "1231米",
        "desc": ""
      },
      {
        "tit": "郑州儿童医院",
        "jl": "1233米",
        "desc": ""
      },
      {
        "tit": "郑州颐和医院-住院部C",
        "jl": "636米",
        "desc": ""
      },
      {
        "tit": "郑州颐和医院-门急诊医技楼",
        "jl": "825米",
        "desc": ""
      }
    ],
    "gw": [
      {
        "tit": "大商超市(宝龙城市广场B区店)",
        "jl": "417米",
        "desc": ""
      },
      {
        "tit": "宝龙城市广场B区",
        "jl": "412米",
        "desc": ""
      },
      {
        "tit": "ARC城市展厅",
        "jl": "77米",
        "desc": ""
      },
      {
        "tit": "丹尼斯全日鲜(老街店)",
        "jl": "757米",
        "desc": ""
      },
      {
        "tit": "郑东如意茶城",
        "jl": "258米",
        "desc": ""
      },
      {
        "tit": "康城·奥特莱斯(宝龙城市广场A区店)",
        "jl": "655米",
        "desc": ""
      },
      {
        "tit": "七事",
        "jl": "252米",
        "desc": ""
      },
      {
        "tit": "蓝城凤起梧桐生活体验馆",
        "jl": "262米",
        "desc": ""
      },
      {
        "tit": "二毛茗茶(天韵街店)",
        "jl": "224米",
        "desc": ""
      },
      {
        "tit": "千盛生活广场",
        "jl": "503米",
        "desc": ""
      }
    ],
    "yh": [
      {
        "tit": "华夏银行24小时自助银行(郑州九如路支行)",
        "jl": "109米",
        "desc": ""
      },
      {
        "tit": "中国银行24小时自助银行(郑州天韵街支行)",
        "jl": "142米",
        "desc": ""
      },
      {
        "tit": "中国银行(郑州天韵街支行)",
        "jl": "158米",
        "desc": ""
      },
      {
        "tit": "中国邮政储蓄银行24小时自助银行(九如路店)",
        "jl": "312米",
        "desc": ""
      },
      {
        "tit": "郑州银行24小时自助银行(宝龙城市广场B区)",
        "jl": "340米",
        "desc": ""
      },
      {
        "tit": "中国银行24小时自助银行(郑州宝龙广场)",
        "jl": "403米",
        "desc": ""
      },
      {
        "tit": "中国银行(宝龙城市广场店)",
        "jl": "405米",
        "desc": ""
      },
      {
        "tit": "广发银行24小时自助银行(宝龙城市广场B区)",
        "jl": "416米",
        "desc": ""
      },
      {
        "tit": "中国工商银行24小时自助银行(郑州宝龙广场支行)",
        "jl": "433米",
        "desc": ""
      },
      {
        "tit": "中国建设银行(宝龙城市广场B区)",
        "jl": "479米",
        "desc": ""
      }
    ],
    "position": 1
  }
]