[
  {
    "dt": [
      {
        "tit": "宏康路文化路",
        "jl": "57米",
        "desc": "186路,b51路,"
      },
      {
        "tit": "龙门路文化路",
        "jl": "64米",
        "desc": "b51路,"
      },
      {
        "tit": "文化路路寨",
        "jl": "184米",
        "desc": "6路,62路,75路,79路,723路,b18路,b52路,s156路,y6路,"
      },
      {
        "tit": "文化路宏康路",
        "jl": "193米",
        "desc": "6路,62路,75路,186路,196路,723路,b52路,s156路,y6路,"
      },
      {
        "tit": "丰庆路宏康路",
        "jl": "194米",
        "desc": "2路,186路,b50路,b51路,y27路,"
      },
      {
        "tit": "丰庆路杲村",
        "jl": "217米",
        "desc": "y27路,"
      },
      {
        "tit": "琉璃寺新村",
        "jl": "406米",
        "desc": "98路,"
      },
      {
        "tit": "宏康路丰庆路",
        "jl": "291米",
        "desc": "2路,b50路,y27路,"
      },
      {
        "tit": "文化路杲村公交站",
        "jl": "418米",
        "desc": "b18路,"
      },
      {
        "tit": "文化路宏康路西",
        "jl": "205米",
        "desc": "b18路,s156路,"
      }
    ],
    "gj": [
      {
        "tit": "育春培训学校",
        "jl": "307米",
        "desc": ""
      },
      {
        "tit": "郑州龙门实验学校",
        "jl": "612米",
        "desc": ""
      },
      {
        "tit": "郑州冠军中学",
        "jl": "1517米",
        "desc": ""
      },
      {
        "tit": "郑州星源外国语学校",
        "jl": "1820米",
        "desc": ""
      },
      {
        "tit": "郑州市第七中学",
        "jl": "2058米",
        "desc": ""
      },
      {
        "tit": "东方剑桥幼儿园",
        "jl": "293米",
        "desc": ""
      },
      {
        "tit": "河南省经济技术中等职业学校",
        "jl": "1679米",
        "desc": ""
      },
      {
        "tit": "河南省劳动干部学校",
        "jl": "1836米",
        "desc": ""
      },
      {
        "tit": "郑州新奇中学",
        "jl": "2322米",
        "desc": ""
      },
      {
        "tit": "郑州市第七中学(丽水校区)",
        "jl": "997米",
        "desc": ""
      }
    ],
    "xx": [
      {
        "tit": "美景万科广场",
        "jl": "1879米",
        "desc": ""
      },
      {
        "tit": "众惠生鲜超市",
        "jl": "337米",
        "desc": ""
      },
      {
        "tit": "好壹佳便利超市",
        "jl": "344米",
        "desc": ""
      },
      {
        "tit": "蔬菜水果超市",
        "jl": "349米",
        "desc": ""
      },
      {
        "tit": "爱便利",
        "jl": "34米",
        "desc": ""
      },
      {
        "tit": "丹尼斯全日鲜(文化二店)",
        "jl": "1388米",
        "desc": ""
      },
      {
        "tit": "泰国天然乳胶生活体验馆",
        "jl": "79米",
        "desc": ""
      },
      {
        "tit": "丹尼斯全日鲜(英才街店)",
        "jl": "1875米",
        "desc": ""
      },
      {
        "tit": "邻家果园",
        "jl": "98米",
        "desc": ""
      },
      {
        "tit": "袜DI家生活馆(三全路店)",
        "jl": "81米",
        "desc": ""
      }
    ],
    "yy": [
      {
        "tit": "中原银行24小时自助银行服务(瀚宇天悦社区支行)",
        "jl": "76米",
        "desc": ""
      },
      {
        "tit": "中原银行(瀚宇天悦社区支行)",
        "jl": "92米",
        "desc": ""
      },
      {
        "tit": "中国工商银行24小时自助银行(郑州文化北路支行)",
        "jl": "134米",
        "desc": ""
      },
      {
        "tit": "中国工商银行(郑州文化北路支行)",
        "jl": "148米",
        "desc": ""
      },
      {
        "tit": "兴业银行(郑州丰庆路支行)",
        "jl": "337米",
        "desc": ""
      },
      {
        "tit": "兴业银行24小时自助银行(郑州丰庆路支行)",
        "jl": "338米",
        "desc": ""
      },
      {
        "tit": "郑州农商银行(琉璃寺支行)",
        "jl": "406米",
        "desc": ""
      },
      {
        "tit": "中国工商银行24小时自助银行(文化北路分理处)",
        "jl": "1247米",
        "desc": ""
      },
      {
        "tit": "中国建设银行(郑州田园新城支行)",
        "jl": "1377米",
        "desc": ""
      },
      {
        "tit": "中国邮政储蓄银行24小时自助银行(郑州市惠济支行)",
        "jl": "1377米",
        "desc": ""
      }
    ],
    "position": 1
  }
]